web/__init__.py
web/base.py
web/cli.py
web/restful.py
web/sql.py
web/utils/__init__.py
web/utils/base.py
wkweb-0.0.0.8.dist-info/LICENSE
wkweb-0.0.0.8.dist-info/METADATA
wkweb-0.0.0.8.dist-info/WHEEL
wkweb-0.0.0.8.dist-info/entry_points.txt
wkweb-0.0.0.8.dist-info/top_level.txt
wkweb-0.0.0.8.dist-info/RECORD
