Metadata-Version: 2.1
Name: wkweb
Version: 0.0.0.8
Summary: A python devkit for web development, based on flask.
Home-page: https://github.com/Peiiii/wkweb
Author: Wang Pei
Author-email: 1535376447@qq.com
License: UNKNOWN
Platform: UNKNOWN
Classifier: Programming Language :: Python :: 3
Classifier: License :: OSI Approved :: MIT License
Classifier: Operating System :: OS Independent
Requires-Python: >=3.0
Requires-Dist: flask
Requires-Dist: jinja2
Requires-Dist: fire
Requires-Dist: wpkit2
Requires-Dist: sqlalchemy
Requires-Dist: pymysql
